rdpurchasesbilling/EcsInterface.py
rdpurchasesbilling/__init__.py
rdpurchasesbilling/mainModel.py
rdpurchasesbilling/metadata.py
rdpurchasesbilling/operation.py
rdpurchasesbilling/utility.py
rdpurchasesbilling-1.2.6.dist-info/METADATA
rdpurchasesbilling-1.2.6.dist-info/WHEEL
rdpurchasesbilling-1.2.6.dist-info/top_level.txt
rdpurchasesbilling-1.2.6.dist-info/RECORD
